driverium/__init__.py
driverium/driverium.py
driverium-1.2.4.dist-info/LICENSE
driverium-1.2.4.dist-info/METADATA
driverium-1.2.4.dist-info/WHEEL
driverium-1.2.4.dist-info/top_level.txt
driverium-1.2.4.dist-info/RECORD
