Metadata-Version: 2.1
Name: driverium
Version: 1.2.4
Summary: Python library that provides functionality for managing and downloading ChromeDriver
Home-page: https://github.com/d3kxrma/driverium
Author: dekxrma
Author-email: qqdjnuxez@gmail.com
License: MIT
Project-URL: Source, https://github.com/d3kxrma/driverium
Keywords: python,selenium,webdriver,chromedriver
Classifier: Development Status :: 5 - Production/Stable
Classifier: Intended Audience :: Developers
Classifier: Operating System :: Microsoft :: Windows :: Windows 10
Classifier: License :: OSI Approved :: MIT License
Classifier: Programming Language :: Python :: 3
License-File: LICENSE
Requires-Dist: requests
Requires-Dist: chrome-version
